wagtail_shortcode/__init__.py
wagtail_shortcode/apps.py
wagtail_shortcode/handlers.py
wagtail_shortcode/models.py
wagtail_shortcode/wagtail_hooks.py
wagtail_shortcode/migrations/__init__.py
wagtail_shortcode/static/wagtail_shortcode/js/wagtail-shortcode.js
wagtail_shortcode/static/wagtail_shortcode/js/wagtail-shortcode.js.LICENSE.txt
wagtail_shortcode-1.0.3.dist-info/LICENSE
wagtail_shortcode-1.0.3.dist-info/WHEEL
wagtail_shortcode-1.0.3.dist-info/METADATA
wagtail_shortcode-1.0.3.dist-info/RECORD
